.gitignore
CHANGELOG.md
README.rst
setup.py
HearPlanetAPI.egg-info/PKG-INFO
HearPlanetAPI.egg-info/SOURCES.txt
HearPlanetAPI.egg-info/dependency_links.txt
HearPlanetAPI.egg-info/requires.txt
HearPlanetAPI.egg-info/top_level.txt
HearPlanetAPI.egg-info/zip-safe
cfg/hearplanet.cfg
examples/example.py
examples/featured_articles.py
examples/poi_location.py
hearplanet/__init__.py
hearplanet/api.py
hearplanet/check_version.py
hearplanet/config.py
hearplanet/defaults.cfg
hearplanet/query/__init__.py
hearplanet/query/base.py
hearplanet/query/read.py
hearplanet/query/table.py
hearplanet/query/utf8_pprint.py
tests/__init__.py
tests/test_api.py