Metadata-Version: 1.1
Name: HearPlanetAPI
Version: 0.1.1
Summary: HearPlanet API driver
Home-page: http://pypi.python.org/pypi/HearPlanetAPI/
Author: Liam Kirsher
Author-email: liam@hearplanet.com
License: UNKNOWN
Keywords: HearPlanet API driver
Platform: UNKNOWN
Classifier: Development Status :: 3 - Alpha
Classifier: Environment :: Console
Classifier: Intended Audience :: Developers
Classifier: License :: OSI Approved :: Apache Software License
Classifier: Natural Language :: English
Classifier: Programming Language :: Python
Classifier: Topic :: Software Development :: Libraries :: Python Modules
